stactools/amazonia_1/__init__.py
stactools/amazonia_1/commands.py
stactools/amazonia_1/constants.py
stactools/amazonia_1/stac.py
stactools_amazonia_1-0.1.3.dist-info/LICENSE
stactools_amazonia_1-0.1.3.dist-info/METADATA
stactools_amazonia_1-0.1.3.dist-info/WHEEL
stactools_amazonia_1-0.1.3.dist-info/top_level.txt
stactools_amazonia_1-0.1.3.dist-info/RECORD
