Metadata-Version: 2.1
Name: stactools-amazonia-1
Version: 0.1.3
Summary: Amazonia-1 on AWS stactools package
Home-page: https://github.com/stactools-packages/amazonia-1
Author: Frederico Liporace
Author-email: liporace@amskepler.com
Project-URL: Issues, https://github.com/stactools-packages/amazonia-1/issues
Keywords: stactools,pystac,catalog,STAC,Amazonia-1
Classifier: Development Status :: 4 - Beta
Classifier: License :: OSI Approved :: Apache Software License
Classifier: Programming Language :: Python :: 3.8
Classifier: Programming Language :: Python :: 3.9
Classifier: Programming Language :: Python :: 3.10
License-File: LICENSE
Requires-Dist: stactools >=0.4.2
Requires-Dist: utm
Requires-Dist: requests
